tarang/__init__.py
tarang/cli.py
tarang/context_collector.py
tarang/stream.py
tarang/client/__init__.py
tarang/client/api_client.py
tarang/client/auth.py
tarang/context/__init__.py
tarang/context/bm25.py
tarang/context/chunker.py
tarang/context/graph.py
tarang/context/indexer.py
tarang/context/retriever.py
tarang/context/skeleton.py
tarang/executor/__init__.py
tarang/executor/diff_apply.py
tarang/executor/linter.py
tarang/ui/__init__.py
tarang/ui/console.py
tarang/ui/diff_viewer.py
tarang/ui/formatter.py
tarang/ui/keyboard.py
tarang/ws/__init__.py
tarang/ws/client.py
tarang/ws/executor.py
tarang/ws/handlers.py
tarang-4.1.0.dist-info/METADATA
tarang-4.1.0.dist-info/WHEEL
tarang-4.1.0.dist-info/entry_points.txt
tarang-4.1.0.dist-info/top_level.txt
tarang-4.1.0.dist-info/RECORD
