Metadata-Version: 2.4
Name: tarang
Version: 4.1.0
Summary: Tarang - AI Coding Agent (Hybrid WebSocket Architecture)
Author-email: Tarang Team <hello@devtarang.ai>
License: MIT
Project-URL: Homepage, https://devtarang.ai
Project-URL: Documentation, https://docs.devtarang.ai
Project-URL: Repository, https://github.com/tarang-ai/tarang-cli
Keywords: ai,coding,assistant,llm,developer-tools
Classifier: Development Status :: 4 - Beta
Classifier: Environment :: Console
Classifier: Intended Audience :: Developers
Classifier: License :: OSI Approved :: MIT License
Classifier: Programming Language :: Python :: 3
Classifier: Programming Language :: Python :: 3.10
Classifier: Programming Language :: Python :: 3.11
Classifier: Programming Language :: Python :: 3.12
Classifier: Topic :: Software Development :: Code Generators
Requires-Python: >=3.10
Requires-Dist: click>=8.0.0
Requires-Dist: httpx>=0.25.0
Requires-Dist: pydantic>=2.0.0
Requires-Dist: python-dotenv>=1.0.0
Requires-Dist: rich>=13.0.0
Requires-Dist: websockets>=12.0
Requires-Dist: prompt_toolkit>=3.0.0
Requires-Dist: rank-bm25>=0.2.2
Requires-Dist: tree-sitter>=0.23.0
Requires-Dist: tree-sitter-python>=0.23.0
Requires-Dist: tree-sitter-javascript>=0.23.0
Requires-Dist: tree-sitter-sql>=0.3.0
Provides-Extra: dev
Requires-Dist: pytest>=7.0.0; extra == "dev"
Requires-Dist: pytest-asyncio>=0.21.0; extra == "dev"
Requires-Dist: ruff>=0.1.0; extra == "dev"
Requires-Dist: mypy>=1.0.0; extra == "dev"
